opengeode/__init__.py
opengeode/__init__.pyi
opengeode/basic.py
opengeode/basic.pyi
opengeode/gdal.py
opengeode/gdal.pyi
opengeode/geometry.py
opengeode/geometry.pyi
opengeode/image.py
opengeode/image.pyi
opengeode/mesh.py
opengeode/mesh.pyi
opengeode/model.py
opengeode/model.pyi
opengeode/py.typed
opengeode/lib64/__init__.pyi
opengeode/lib64/libOpenGeode_basic.so
opengeode/lib64/libOpenGeode_geometry.so
opengeode/lib64/libOpenGeode_image.so
opengeode/lib64/libOpenGeode_mesh.so
opengeode/lib64/libOpenGeode_model.so
opengeode/lib64/libabsl_bad_any_cast_impl.so
opengeode/lib64/libabsl_bad_any_cast_impl.so.0
opengeode/lib64/libabsl_bad_optional_access.so
opengeode/lib64/libabsl_bad_optional_access.so.0
opengeode/lib64/libabsl_bad_variant_access.so
opengeode/lib64/libabsl_bad_variant_access.so.0
opengeode/lib64/libabsl_base.so
opengeode/lib64/libabsl_base.so.0
opengeode/lib64/libabsl_city.so
opengeode/lib64/libabsl_city.so.0
opengeode/lib64/libabsl_civil_time.so
opengeode/lib64/libabsl_civil_time.so.0
opengeode/lib64/libabsl_cord.so
opengeode/lib64/libabsl_cord.so.0
opengeode/lib64/libabsl_cord_internal.so
opengeode/lib64/libabsl_cord_internal.so.0
opengeode/lib64/libabsl_cordz_functions.so
opengeode/lib64/libabsl_cordz_functions.so.0
opengeode/lib64/libabsl_cordz_handle.so
opengeode/lib64/libabsl_cordz_handle.so.0
opengeode/lib64/libabsl_cordz_info.so
opengeode/lib64/libabsl_cordz_info.so.0
opengeode/lib64/libabsl_cordz_sample_token.so
opengeode/lib64/libabsl_cordz_sample_token.so.0
opengeode/lib64/libabsl_crc32c.so
opengeode/lib64/libabsl_crc32c.so.0
opengeode/lib64/libabsl_crc_cord_state.so
opengeode/lib64/libabsl_crc_cord_state.so.0
opengeode/lib64/libabsl_crc_cpu_detect.so
opengeode/lib64/libabsl_crc_cpu_detect.so.0
opengeode/lib64/libabsl_crc_internal.so
opengeode/lib64/libabsl_crc_internal.so.0
opengeode/lib64/libabsl_debugging_internal.so
opengeode/lib64/libabsl_debugging_internal.so.0
opengeode/lib64/libabsl_decode_rust_punycode.so
opengeode_core-15.30.13.dist-info/METADATA
opengeode_core-15.30.13.dist-info/WHEEL
opengeode_core-15.30.13.dist-info/top_level.txt
opengeode_core-15.30.13.dist-info/RECORD
