Metadata-Version: 2.4
Name: OpenGeode-core
Version: 15.30.13
Summary: Open source framework for representing and manipulating geometric models
Author-email: Geode-solutions <contact@geode-solutions.com>
License: MIT
Requires-Python: <3.13,>=3.9
